cftscal/__init__.py
cftscal/api.py
cftscal/main.py
cftscal/objects.py
cftscal/util.py
cftscal/version.py
cftscal/paradigms/__init__.py
cftscal/paradigms/amplifier_calibration.enaml
cftscal/paradigms/calibration_mixins.enaml
cftscal/paradigms/input_amplifier_calibration.enaml
cftscal/paradigms/monitor.enaml
cftscal/paradigms/objects.enaml
cftscal/paradigms/pistonphone_calibration.enaml
cftscal/paradigms/pt_calibration.enaml
cftscal/paradigms/speaker_calibration.enaml
cftscal/plugins/__init__.py
cftscal/plugins/calibration_window.enaml
cftscal/plugins/manifest.enaml
cftscal/plugins/settings.py
cftscal/plugins/widgets.enaml
cftscal/plugins/inear/__init__.py
cftscal/plugins/inear/manifest.enaml
cftscal/plugins/inear/settings.py
cftscal/plugins/inear/view.enaml
cftscal/plugins/input_amplifier/__init__.py
cftscal/plugins/input_amplifier/manifest.enaml
cftscal/plugins/input_amplifier/settings.py
cftscal/plugins/input_amplifier/view.enaml
cftscal/plugins/microphone/__init__.py
cftscal/plugins/microphone/manifest.enaml
cftscal/plugins/microphone/settings.py
cftscal/plugins/microphone/view.enaml
cftscal/plugins/speaker/__init__.py
cftscal/plugins/speaker/manifest.enaml
cftscal/plugins/speaker/settings.py
cftscal/plugins/speaker/view.enaml
cftscal/plugins/starship/__init__.py
cftscal/plugins/starship/manifest.enaml
cftscal/plugins/starship/settings.py
cftscal/plugins/starship/view.enaml
cftscal-0.2.3.dist-info/licenses/LICENSE.txt
cftscal-0.2.3.dist-info/METADATA
cftscal-0.2.3.dist-info/WHEEL
cftscal-0.2.3.dist-info/entry_points.txt
cftscal-0.2.3.dist-info/top_level.txt
cftscal-0.2.3.dist-info/RECORD
