Metadata-Version: 2.4
Name: cftscal
Version: 0.2.3
Summary: Paradigms for running calibrations required for CFTS
Author-email: Brad Buran <buran@ohsu.edu>
Maintainer-email: Brad Buran <buran@ohsu.edu>
License: MIT License
Requires-Python: >=3.7
License-File: LICENSE.txt
Requires-Dist: cftsdata
Requires-Dist: psiexperiment
Requires-Dist: enaml[qt5-pyqt]>=0.13.0
Requires-Dist: enamlx>=0.6.2
Requires-Dist: tqdm
Dynamic: license-file
